colored_slack_log_handler/__init__.py
colored_slack_log_handler-0.0.6.dist-info/METADATA
colored_slack_log_handler-0.0.6.dist-info/RECORD
colored_slack_log_handler-0.0.6.dist-info/WHEEL
colored_slack_log_handler-0.0.6.dist-info/top_level.txt
tests/__init__.py
tests/test_colored_slack_log_handler.py
