Metadata-Version: 2.1
Name: colored-slack-log-handler
Version: 0.0.6
Summary: Python color-coding Slack log handler
Home-page: https://github.com/shibataka000/colored_slack_log_handler
Author: shibataka000
Author-email: UNKNOWN
License: MIT
Platform: UNKNOWN
Requires-Dist: requests
